.gitignore
LICENSE
MANIFEST.in
README.md
pyproject.toml
setup.py
scratch/uncategorized.md
scripts/eg_prybahr_script.py
src/prybahr/__init__.py
src/prybahr.egg-info/PKG-INFO
src/prybahr.egg-info/SOURCES.txt
src/prybahr.egg-info/dependency_links.txt
src/prybahr.egg-info/top_level.txt
tests/conftest.py
tests/test_a.py