Metadata-Version: 1.1
Name: prybahr
Version: 0.1.1
Summary: prybahr ...
Home-page: https://TBD-36A8DB87.nfwatson.com/TBD-36A8DB87
Author: Dev@NFWatson.Com
Author-email: dev@nfwatson.com
License: MIT
Platform: UNKNOWN
Classifier: Programming Language :: Python :: 3
Classifier: License :: OSI Approved :: MIT License
